leann_backend_hnsw/_swigfaiss.so
leann_backend_hnsw/class_wrappers.py
leann_backend_hnsw/extra_wrappers.py
leann_backend_hnsw/__init__.py
leann_backend_hnsw/faiss.py
leann_backend_hnsw/array_conversions.py
leann_backend_hnsw/loader.py
leann_backend_hnsw/convert_to_csr.py
leann_backend_hnsw/hnsw_backend.py
leann_backend_hnsw/hnsw_embedding_server.py
leann_backend_hnsw/.dylibs/libsodium.26.dylib
leann_backend_hnsw/.dylibs/libomp.dylib
leann_backend_hnsw/.dylibs/libzmq.5.dylib
include/msgpack.hpp
include/msgpack/unpack_decl.hpp
include/msgpack/gcc_atomic.hpp
include/msgpack/parse_return.hpp
include/msgpack/sbuffer.hpp
include/msgpack/fbuffer.hpp
include/msgpack/type.hpp
include/msgpack/meta_decl.hpp
include/msgpack/sysdep.hpp
include/msgpack/x3_parse.hpp
include/msgpack/object_decl.hpp
include/msgpack/object_fwd_decl.hpp
include/msgpack/unpack.hpp
include/msgpack/x3_parse_decl.hpp
include/msgpack/meta.hpp
include/msgpack/fbuffer_decl.hpp
include/msgpack/unpack_exception.hpp
include/msgpack/parse_decl.hpp
include/msgpack/create_object_visitor.hpp
include/msgpack/object_fwd.hpp
include/msgpack/iterator_decl.hpp
include/msgpack/version.hpp
include/msgpack/zbuffer_decl.hpp
include/msgpack/null_visitor.hpp
include/msgpack/version_master.hpp
include/msgpack/object.hpp
include/msgpack/x3_unpack.hpp
include/msgpack/zbuffer.hpp
include/msgpack/cpp_config_decl.hpp
include/msgpack/assert.hpp
include/msgpack/pack.hpp
include/msgpack/x3_unpack_decl.hpp
include/msgpack/sbuffer_decl.hpp
include/msgpack/zone_decl.hpp
include/msgpack/vrefbuffer_decl.hpp
include/msgpack/null_visitor_decl.hpp
include/msgpack/vrefbuffer.hpp
include/msgpack/zone.hpp
include/msgpack/preprocessor.hpp
include/msgpack/unpack_define.hpp
include/msgpack/iterator.hpp
include/msgpack/parse.hpp
include/msgpack/cpp_version.hpp
include/msgpack/predef.h
include/msgpack/pack_decl.hpp
include/msgpack/cpp_config.hpp
leann_backend_hnsw-0.3.6.dist-info/RECORD
leann_backend_hnsw-0.3.6.dist-info/WHEEL
leann_backend_hnsw-0.3.6.dist-info/METADATA
