Metadata-Version: 2.2
Name: leann-backend-hnsw
Version: 0.3.6
Summary: Custom-built HNSW (Faiss) backend for the Leann toolkit.
Requires-Dist: leann-core==0.3.6
Requires-Dist: numpy
Requires-Dist: pyzmq>=23.0.0
Requires-Dist: msgpack>=1.0.0
